spiegel_scraper/__init__.py
spiegel_scraper/archive.py
spiegel_scraper/article.py
spiegel_scraper/comments.py
spiegel_scraper/constants.py
spiegel_scraper-1.1.1.dist-info/METADATA
spiegel_scraper-1.1.1.dist-info/WHEEL
spiegel_scraper-1.1.1.dist-info/top_level.txt
spiegel_scraper-1.1.1.dist-info/RECORD
