Metadata-Version: 2.1
Name: spiegel-scraper
Version: 1.1.1
Summary: Scrape article metadata and comments from DER SPIEGEL
Home-page: https://github.com/ietz/spiegel-scraper
Author: Tim Pietz
Author-email: tim@pietz.me
License: MIT
Platform: UNKNOWN
Classifier: License :: OSI Approved :: MIT License
Classifier: Programming Language :: Python :: 3
Classifier: Programming Language :: Python :: 3.8
Requires-Dist: cssselect
Requires-Dist: dateparser
Requires-Dist: lxml
Requires-Dist: requests
Requires-Dist: tldextract
